Workbook

Sheet Sales
A1: Tanggal | B1: Tunai (IDR) | C1: QRIS (IDR) | D1: Transfer (IDR) | E1: Habis Terjual? (Y/N) | F1: Sisa/Waste (IDR) | G1: Note
A2: 46328 | B2: 1200000 | C2: 250000 | D2: 550000 | E2: Y | F2: 0 | G2: Hari senin minggu pertama PNS Gajian
A3: 46329 | B3: 500000 | C3: 1200000 | D3: 250000 | E3: Y | F3: 0 | G3: Hari kedua minggu pertama PNS Gajian
A4: 46330 | B4: 1200000 | C4: 120000 | D4: 600000 | E4: N | F4: 20000 | G4: Mendung dan hujan
A5: 46331 | B5: 750000 | C5: 800000 | D5: 250000 | E5: N | F5: 200000 | G5: Jam makan siang hujan
A6: 46332 | B6: 600000 | C6: 700000 | D6: 250000 | E6: Y | F6: 0 | G6: Mahasiswa dan paket murah banyak laku
A7: 46333 | B7: 500000 | C7: 1300000 | D7: 200000 | E7: Y | F7: 0 | G7: Weekend hari keluarga
A8: 46334 | B8: 1200000 | C8: 250000 | D8: 550000 | E8: Y | F8: 0 | G8: Weekend hari keluarga

Sheet Expense
A1: Tanggal | B1: Kategori | C1: Deskripsi | D1: Jumlah (IDR) | E1: Metode
A2: 46326 | B2: Bahan Baku | C2: babi 50 kg, Pasar Gunungsitoli | D2: 5000000 | E2: Tunai
A3: 46326 | B3: Bahan Baku | C3: Beras 20 kg, Pasar Gunungsitoli | D3: 450000 | E3: Tunai
A4: 46326 | B4: Bahan Minum | C4: Gula 5 kg, Pasar Gunungsitoli | D4: 100000 | E4: Tunai
A5: 46326 | B5: Bahan Minum | C5: Teh 2 Kotak, Pasar Gunungsitoli | D5: 25000 | E5: Qris
A6: 46326 | B6: Bahan Minum | C6: Jeruk 4 kg, Pasar Gunungsitoli | D6: 80000 | E6: Transfer
A7: 46326 | B7: Bahan masak | C7: Gas 5 kg | D7: 20000 | E7: Qris
A8: 46326 | B8: Bahan Baku | C8: Bumbu Dapur paket | D8: 250000 | E8: Tunai
A9: 46326 | B9: Bahan Minum | C9: Air 10 galon | D9: 50000 | E9: Transfer
A10: 46326 | B10: Bahan Masak | C10: Kayu bakar | D10: 50000 | E10: Tunai
A11: 46326 | B11: Bahan Baku | C11: Sayur mayur | D11: 100000 | E11: Tunai
A12: 46327 | B12: Bahan Baku | C12: Bumbu Dapur paket | D12: 250000 | E12: Tunai
A13: 46327 | B13: Bahan Minum | C13: Teh 2 Kotak, Pasar Gunungsitoli | D13: 100000 | E13: Qris
A14: 46327 | B14: Bahan Bungkus | C14: Kertas Nasi | D14: 100000 | E14: Qris
A15: 46337 | B15: Operasional Lain | D15: 250000 | E15: Tunai
A16: 46338 | B16: Renovasi | D16: 250000 | E16: Tunai

Sheet Fix Cost
A2: Date | B2: Item | C2: Jumlah (IDR)
A3: 46328 | B3: Sewa | C3: =15000000/12 -> 1250000
A4: 46328 | B4: Listrik | C4: 203000
A5: 46328 | B5: Internet | C5: 319150
A6: 46328 | B6: Aplikasi | C6: 259475
A7: 46332 | B7: Gaji per staf | C7: 1600000
A8: 46332 | B8: Bpjs Kesehatan | C8: 102500
A9: 46332 | B9: Bpjs Ketenagakerjaan | C9: 100000
A10: 46332 | B10: Admin bank | C10: 25000
A11: 46336 | B11: Operasional Asset | C11: 0

Sheet Category
A1: Kategori
A2: Bahan Minum
A3: Bahan Masak
A4: Gas
A5: Bahan Baku
A6: Sewa
A7: Listrik
A8: Internet
A9: Aplikasi
A10: Gaji per staf
A11: Bpjs Kesehatan
A12: Bpjs Ketenagakerjaan
... A16: Renovasi

Sheet Dashboard
A1: KPI
B2: Total Pendapatan | C2: Total Pengeluaran | D2: Laba / Rugi | E2: Margin % | F2: Total Waste
B3: =SUM(Sales!B2:D8) -> 13220000 | C3: =SUM(Expense!D2:D16)+SUM('Fix Cost'!C3:C11) -> 10934125 | D3: =B3-C3 -> 2285875 | E3: =IF(B3=0,0,D3/B3) -> 0.17291036 | F3: =SUM(Sales!F2:F8) -> 220000
A5: Payment Method Split
B6: Tunai | C6: QRIS | D6: Transfer
B7: =SUM(Sales!B2:B8) -> 5950000 | C7: =SUM(Sales!C2:C8) -> 4620000 | D7: =SUM(Sales!D2:D8) -> 2650000
B8: =SUM(Sales!B2:B8)/B3 -> 0.45007564 | C8: =SUM(Sales!C2:C8)/B3 -> 0.3494705 | D8: =SUM(Sales!D2:D8)/B3 -> 0.20045386
A10: Grafik Pendapatan Harian
A20: Breakdown Pengeluaran per Kategori
H21: Bahan Minum | I21: =SUMIF(Expense!$B$2:$B$16,Dashboard!H21,Expense!$D$2:$D$16) -> 355000
H22: Bahan Masak | I22: =SUMIF(Expense!$B$2:$B$16,Dashboard!H22,Expense!$D$2:$D$16) -> 70000
H23: Bahan Baku | I23: =SUMIF(Expense!$B$2:$B$16,Dashboard!H23,Expense!$D$2:$D$16) -> 6050000
H24: Bahan Bungkus | I24: =SUMIF(Expense!$B$2:$B$16,Dashboard!H24,Expense!$D$2:$D$16) -> 100000
H25: Sewa | I25: =SUMIF(Expense!$B$2:$B$13,Dashboard!H25,Expense!$D$2:$D$13) -> 0
H26: Listrik | I26: =SUMIF(Expense!$B$2:$B$13,Dashboard!H26,Expense!$D$2:$D$13) -> 0
H27: Internet | I27: =SUMIF(Expense!$B$2:$B$13,Dashboard!H27,Expense!$D$2:$D$13) -> 0
H28: Aplikasi | I28: =SUMIF(Expense!$B$2:$B$13,Dashboard!H28,Expense!$D$2:$D$13) -> 0
H29: Gaji per staf | I29: =SUMIF(Expense!$B$2:$B$13,Dashboard!H29,Expense!$D$2:$D$13) -> 0
A30: Tren Waste | H30: Bpjs Kesehatan | I30: =SUMIF(Expense!$B$2:$B$13,Dashboard!H30,Expense!$D$2:$D$13) -> 0
H31: Bpjs Ketenagakerjaan | I31: =SUMIF(Expense!$B$2:$B$13,Dashboard!H31,Expense!$D$2:$D$13) -> 0
H32: Admin bank | I32: =SUMIF(Expense!$B$2:$B$13,Dashboard!H32,Expense!$D$2:$D$13) -> 0
H33: Operasional Asset | I33: =SUMIF(Expense!$B$2:$B$13,Dashboard!H33,Expense!$D$2:$D$13) -> 0
H34: Operasional Lain | I34: =SUMIF(Expense!$B$2:$B$13,Dashboard!H34,Expense!$D$2:$D$13) -> 0
H35: Renovasi | I35: =SUMIF(Expense!$B$2:$B$13,Dashboard!H35,Expense!$D$2:$D$13) -> 0

Sheet LabaRugi
A1: Pendapatan
A2: Tunai | B2: =SUM(Sales!B2:B8) -> 5950000
A3: Qris | B3: =SUM(Sales!C2:C8) -> 4620000
A4: Transfer | B4: =SUM(Sales!D2:D8) -> 2650000
A5: Total Pendapatan | B5: =SUM(B2:B4) -> 13220000
A7: HPP (Harga Pokok Penjualan)
A8: Bahan Baku | B8: =SUMIF(Expense!B2:B13,"bahan baku",Expense!D2:D13) -> 6050000
A9: Bahan Minum | B9: =SUMIF(Expense!B2:B13,"bahan minum",Expense!D2:D13) -> 355000
A10: Bahan Masak | B10: =SUMIF(Expense!B2:B13,"bahan masak",Expense!D2:D13) -> 70000
A11: Kemasaan | B11: =SUMIF(Expense!B2:B16,"bahan bungkus",Expense!D2:D16) -> 100000
A12: Total HPP | B12: =SUM(B8:B11) -> 6575000
A14: Laba Kotor | B14: =B5-B12 -> 6645000
A15: Margin Kotor % | B15: =B14/B5 -> 0.5026475
A17: Biaya Operasional (Fix Cost)
A18: Sewa | B18: =SUMIF('Fix Cost'!$B$3:$B$11,"sewa",'Fix Cost'!$C$3:$C$11) -> 1250000
A19: Listrik | B19: =SUMIF('Fix Cost'!$B$3:$B$11,"listrik",'Fix Cost'!$C$3:$C$11) -> 203000
A20: Internet | B20: =SUMIF('Fix Cost'!$B$3:$B$11,"internet",'Fix Cost'!$C$3:$C$11) -> 319150
A21: Aplikasi | B21: =SUMIF('Fix Cost'!$B$3:$B$11,"aplikasi",'Fix Cost'!$C$3:$C$11) -> 259475
A22: Gaji per staf | B22: =SUMIF('Fix Cost'!$B$3:$B$11,"gaji per staf",'Fix Cost'!$C$3:$C$11) -> 1600000
A23: Bpjs Kesehatan | B23: =SUMIF('Fix Cost'!$B$3:$B$11,"bpjs kesehatan",'Fix Cost'!$C$3:$C$11) -> 102500
A24: Bpjs Ketenagakerjaan | B24: =SUMIF('Fix Cost'!$B$3:$B$11,"bpjs ketenagakerjaan",'Fix Cost'!$C$3:$C$11) -> 100000
A25: Admin bank | B25: =SUMIF('Fix Cost'!$B$3:$B$11,"admin bank",'Fix Cost'!$C$3:$C$11) -> 25000
A26: Operasional Lain | B26: =SUMIF(Expense!B2:B16,"operasional lain",Expense!D2:D16) -> 250000
A27: Renovasi | B27: =SUMIF(Expense!B2:B16,"renovasi",Expense!D2:D16) -> 250000
A28: Total Biaya Operasional | B28: =SUM(B18:B27) -> 4359125
A30: Laba Bersih | B30: =B14-B28 -> 2285875
A31: Margin Bersih % | B31: =B30/B5 -> 0.17291036

Sheet BreakEven
A1: Total Biaya Operasional (Fixed) | B1: =LabaRugi!B28 -> 4359125
A2: Margin Kotor % | B2: =LabaRugi!B15 -> 0.5026475
A4: Pendapatan Break-Even (bulanan) | B4: =LabaRugi!B28/LabaRugi!B15 -> 8672329.9
A5: Pendapatan Break-Even (Harian) | B5: =B4/30 -> 289077.66
A7: Scenario | B7: Monthly Revenue | C7: Laba Bersih
A8: Sepi (Quite) | B8: =B4*0.8 -> 6937864 | C8: =B8*LabaRugi!B15-LabaRugi!B28 -> -871825
A9: Normal | B9: =B4*1.2 -> 10406796 | C9: =B9*LabaRugi!B15-LabaRugi!B28 -> 871825
A10: Ramai (Strong) | B10: =B4*1.6 -> 13875728 | C10: =B10*LabaRugi!B15-LabaRugi!B28 -> 2615475

Sheet Sheet4
