Workbook

Sheet Pricing
A1: Category | B1: Item | C1: Price (IDR)
A2: Package | B2: Single | C2: 40000
A3: Package | B3: Couple | C3: 70000
A4: Package | B4: Trio | C4: 100000
A5: Package | B5: Group of 4 | C5: 135000
A6: Package | B6: Group of 5 | C6: 160000
A7: Package | B7: Group of 6 | C7: 185000
A8: Package | B8: Group of 7 | C8: 210000
A9: Package | B9: Group of 8 | C9: 235000
A10: Add on | B10: Extra 10 minutes | C10: 30000
A11: Add on | B11: Extra 15 minutes | C11: 50000
A12: Add on | B12: Extra 20 minutes | C12: 60000
A13: Add on | B13: Extra background | C13: 15000
... A18: Costume | B18: Animal | C18: 15000

Sheet Order
A1: Tanggal | B1: Jam | C1: Paket | D1: Add-on 1 | E1: Add-on 2 | F1: Add-on 3 | G1: Total (IDR) | H1: Payment Method
A2: 46204 | B2: 0.5 | C2: Couple | G2: =IFERROR(VLOOKUP(C2,Pricing!$B$2:$C$18,2,0),0)+IFERROR(VLOOKUP(D2,Pricing!$B$2:$C$18,2,0),0)+IFERROR(VLOOKUP(E2,Pricing!$B$2:$C$18,2,0),0)+IFERROR(VLOOKUP(F2,Pricing!$B$2:$C$18,2,0),0) -> 70000
A3: 46204 | B3: 0.72916667 | C3: Group of 4 | G3: =IFERROR(VLOOKUP(C3,Pricing!$B$2:$C$18,2,0),0)+IFERROR(VLOOKUP(D3,Pricing!$B$2:$C$18,2,0),0)+IFERROR(VLOOKUP(E3,Pricing!$B$2:$C$18,2,0),0)+IFERROR(VLOOKUP(F3,Pricing!$B$2:$C$18,2,0),0) -> 135000
A4: 46205 | B4: 0.52083333 | C4: Group of 4 | G4: =IFERROR(VLOOKUP(C4,Pricing!$B$2:$C$18,2,0),0)+IFERROR(VLOOKUP(D4,Pricing!$B$2:$C$18,2,0),0)+IFERROR(VLOOKUP(E4,Pricing!$B$2:$C$18,2,0),0)+IFERROR(VLOOKUP(F4,Pricing!$B$2:$C$18,2,0),0) -> 135000
A5: 46205 | B5: 0.64583333 | C5: Single | G5: =IFERROR(VLOOKUP(C5,Pricing!$B$2:$C$18,2,0),0)+IFERROR(VLOOKUP(D5,Pricing!$B$2:$C$18,2,0),0)+IFERROR(VLOOKUP(E5,Pricing!$B$2:$C$18,2,0),0)+IFERROR(VLOOKUP(F5,Pricing!$B$2:$C$18,2,0),0) -> 40000
A6: 46205 | B6: 0.66666667 | C6: Group of 4 | G6: =IFERROR(VLOOKUP(C6,Pricing!$B$2:$C$18,2,0),0)+IFERROR(VLOOKUP(D6,Pricing!$B$2:$C$18,2,0),0)+IFERROR(VLOOKUP(E6,Pricing!$B$2:$C$18,2,0),0)+IFERROR(VLOOKUP(F6,Pricing!$B$2:$C$18,2,0),0) -> 135000
A7: 46205 | B7: 0.70833333 | C7: Single | G7: =IFERROR(VLOOKUP(C7,Pricing!$B$2:$C$18,2,0),0)+IFERROR(VLOOKUP(D7,Pricing!$B$2:$C$18,2,0),0)+IFERROR(VLOOKUP(E7,Pricing!$B$2:$C$18,2,0),0)+IFERROR(VLOOKUP(F7,Pricing!$B$2:$C$18,2,0),0) -> 40000
A8: 46206 | B8: 0.60416667 | C8: Couple | G8: =IFERROR(VLOOKUP(C8,Pricing!$B$2:$C$18,2,0),0)+IFERROR(VLOOKUP(D8,Pricing!$B$2:$C$18,2,0),0)+IFERROR(VLOOKUP(E8,Pricing!$B$2:$C$18,2,0),0)+IFERROR(VLOOKUP(F8,Pricing!$B$2:$C$18,2,0),0) -> 70000
A9: 46206 | B9: 0.66666667 | C9: Couple | D9: Animal | G9: =IFERROR(VLOOKUP(C9,Pricing!$B$2:$C$18,2,0),0)+IFERROR(VLOOKUP(D9,Pricing!$B$2:$C$18,2,0),0)+IFERROR(VLOOKUP(E9,Pricing!$B$2:$C$18,2,0),0)+IFERROR(VLOOKUP(F9,Pricing!$B$2:$C$18,2,0),0) -> 85000
A10: 46207 | B10: 0.4375 | C10: Couple | G10: =IFERROR(VLOOKUP(C10,Pricing!$B$2:$C$18,2,0),0)+IFERROR(VLOOKUP(D10,Pricing!$B$2:$C$18,2,0),0)+IFERROR(VLOOKUP(E10,Pricing!$B$2:$C$18,2,0),0)+IFERROR(VLOOKUP(F10,Pricing!$B$2:$C$18,2,0),0) -> 70000
A11: 46207 | B11: 0.5 | C11: Couple | G11: =IFERROR(VLOOKUP(C11,Pricing!$B$2:$C$18,2,0),0)+IFERROR(VLOOKUP(D11,Pricing!$B$2:$C$18,2,0),0)+IFERROR(VLOOKUP(E11,Pricing!$B$2:$C$18,2,0),0)+IFERROR(VLOOKUP(F11,Pricing!$B$2:$C$18,2,0),0) -> 70000
A12: 46207 | B12: 0.70833333 | C12: Trio | G12: =IFERROR(VLOOKUP(C12,Pricing!$B$2:$C$18,2,0),0)+IFERROR(VLOOKUP(D12,Pricing!$B$2:$C$18,2,0),0)+IFERROR(VLOOKUP(E12,Pricing!$B$2:$C$18,2,0),0)+IFERROR(VLOOKUP(F12,Pricing!$B$2:$C$18,2,0),0) -> 100000
G13: =IFERROR(VLOOKUP(C13,Pricing!$B$2:$C$18,2,0),0)+IFERROR(VLOOKUP(D13,Pricing!$B$2:$C$18,2,0),0)+IFERROR(VLOOKUP(E13,Pricing!$B$2:$C$18,2,0),0)+IFERROR(VLOOKUP(F13,Pricing!$B$2:$C$18,2,0),0) -> 0
G14: =IFERROR(VLOOKUP(C14,Pricing!$B$2:$C$18,2,0),0)+IFERROR(VLOOKUP(D14,Pricing!$B$2:$C$18,2,0),0)+IFERROR(VLOOKUP(E14,Pricing!$B$2:$C$18,2,0),0)+IFERROR(VLOOKUP(F14,Pricing!$B$2:$C$18,2,0),0) -> 0
G15: =IFERROR(VLOOKUP(C15,Pricing!$B$2:$C$18,2,0),0)+IFERROR(VLOOKUP(D15,Pricing!$B$2:$C$18,2,0),0)+IFERROR(VLOOKUP(E15,Pricing!$B$2:$C$18,2,0),0)+IFERROR(VLOOKUP(F15,Pricing!$B$2:$C$18,2,0),0) -> 0
G16: =IFERROR(VLOOKUP(C16,Pricing!$B$2:$C$18,2,0),0)+IFERROR(VLOOKUP(D16,Pricing!$B$2:$C$18,2,0),0)+IFERROR(VLOOKUP(E16,Pricing!$B$2:$C$18,2,0),0)+IFERROR(VLOOKUP(F16,Pricing!$B$2:$C$18,2,0),0) -> 0
G17: =IFERROR(VLOOKUP(C17,Pricing!$B$2:$C$18,2,0),0)+IFERROR(VLOOKUP(D17,Pricing!$B$2:$C$18,2,0),0)+IFERROR(VLOOKUP(E17,Pricing!$B$2:$C$18,2,0),0)+IFERROR(VLOOKUP(F17,Pricing!$B$2:$C$18,2,0),0) -> 0
G18: =IFERROR(VLOOKUP(C18,Pricing!$B$2:$C$18,2,0),0)+IFERROR(VLOOKUP(D18,Pricing!$B$2:$C$18,2,0),0)+IFERROR(VLOOKUP(E18,Pricing!$B$2:$C$18,2,0),0)+IFERROR(VLOOKUP(F18,Pricing!$B$2:$C$18,2,0),0) -> 0
G19: =IFERROR(VLOOKUP(C19,Pricing!$B$2:$C$18,2,0),0)+IFERROR(VLOOKUP(D19,Pricing!$B$2:$C$18,2,0),0)+IFERROR(VLOOKUP(E19,Pricing!$B$2:$C$18,2,0),0)+IFERROR(VLOOKUP(F19,Pricing!$B$2:$C$18,2,0),0) -> 0
G20: =IFERROR(VLOOKUP(C20,Pricing!$B$2:$C$18,2,0),0)+IFERROR(VLOOKUP(D20,Pricing!$B$2:$C$18,2,0),0)+IFERROR(VLOOKUP(E20,Pricing!$B$2:$C$18,2,0),0)+IFERROR(VLOOKUP(F20,Pricing!$B$2:$C$18,2,0),0) -> 0
G21: =IFERROR(VLOOKUP(C21,Pricing!$B$2:$C$18,2,0),0)+IFERROR(VLOOKUP(D21,Pricing!$B$2:$C$18,2,0),0)+IFERROR(VLOOKUP(E21,Pricing!$B$2:$C$18,2,0),0)+IFERROR(VLOOKUP(F21,Pricing!$B$2:$C$18,2,0),0) -> 0
G22: =IFERROR(VLOOKUP(C22,Pricing!$B$2:$C$18,2,0),0)+IFERROR(VLOOKUP(D22,Pricing!$B$2:$C$18,2,0),0)+IFERROR(VLOOKUP(E22,Pricing!$B$2:$C$18,2,0),0)+IFERROR(VLOOKUP(F22,Pricing!$B$2:$C$18,2,0),0) -> 0
G23: =IFERROR(VLOOKUP(C23,Pricing!$B$2:$C$18,2,0),0)+IFERROR(VLOOKUP(D23,Pricing!$B$2:$C$18,2,0),0)+IFERROR(VLOOKUP(E23,Pricing!$B$2:$C$18,2,0),0)+IFERROR(VLOOKUP(F23,Pricing!$B$2:$C$18,2,0),0) -> 0
G24: =IFERROR(VLOOKUP(C24,Pricing!$B$2:$C$18,2,0),0)+IFERROR(VLOOKUP(D24,Pricing!$B$2:$C$18,2,0),0)+IFERROR(VLOOKUP(E24,Pricing!$B$2:$C$18,2,0),0)+IFERROR(VLOOKUP(F24,Pricing!$B$2:$C$18,2,0),0) -> 0
... G200: =IFERROR(VLOOKUP(C200,Pricing!$B$2:$C$18,2,0),0)+IFERROR(VLOOKUP(D200,Pricing!$B$2:$C$18,2,0),0)+IFERROR(VLOOKUP(E200,Pricing!$B$2:$C$18,2,0),0)+IFERROR(VLOOKUP(F200,Pricing!$B$2:$C$18,2,0),0) -> 0

Sheet Expense
A1: Dates | B1: Category | C1: Description | D1: Total | E1: Method
A2: 46228 | B2: Salary | C2: Gaji operator | D2: 1706000 | E2: Transfer
A3: 46228 | B3: BPJS | C3: BPJS kesehatan | D3: 102500 | E3: Transfer
A4: 46220 | B4: Electricity | C4: Listrik | D4: 203000 | E4: Transfer
A5: 46216 | B5: Internet | C5: Indihome | D5: 316350 | E5: Transfer
A6: 46205 | B6: Apps | C6: Adobe lightroom | D6: 259475 | E6: Transfer
A7: 46232 | B7: Other Operational | C7: Kertas foto | D7: 223800 | E7: Transfer

Sheet Category
A1: Salary
A2: BPJS
A3: Rent
A4: Electricity
A5: Internet
A6: Apps
A7: Photo paper
A8: Printer tint
A9: Battery
A10: Other Operational
A11: Assets
